easymaker/__init__.py
easymaker/__main__.py
easymaker/initializer.py
easymaker/api/__init__.py
easymaker/api/api_sender.py
easymaker/api/request_body.py
easymaker/batch_inference/__init__.py
easymaker/batch_inference/batch_inference.py
easymaker/cli/__init__.py
easymaker/cli/cli.py
easymaker/common/__init__.py
easymaker/common/codes.py
easymaker/common/constants.py
easymaker/common/environment_variables.py
easymaker/common/exceptions.py
easymaker/common/image.py
easymaker/common/instance_type.py
easymaker/common/parameter.py
easymaker/common/storage.py
easymaker/common/base_model/__init__.py
easymaker/common/base_model/easymaker_base_model.py
easymaker/common/base_model/hyperparameter_tuning_base_model.py
easymaker/common/base_model/training_base_model.py
easymaker/common/utils/__init__.py
easymaker/endpoint/__init__.py
easymaker/endpoint/api_spec.py
easymaker/endpoint/components.py
easymaker/endpoint/endpoint.py
easymaker/endpoint/utils.py
easymaker/experiment/__init__.py
easymaker/experiment/experiment.py
easymaker/log/__init__.py
easymaker/log/logger.py
easymaker/model/__init__.py
easymaker/model/model.py
easymaker/model_evaluation/__init__.py
easymaker/model_evaluation/model_evaluation.py
easymaker/model_evaluation/model_evaluation_metrics.py
easymaker/pipeline/__init__.py
easymaker/pipeline/components.py
easymaker/pipeline/pipeline.py
easymaker/pipeline/pipeline_recurring_run.py
easymaker/pipeline/pipeline_run.py
easymaker/sample/__init__.py
easymaker/sample/gov_sample.py
easymaker/sample/sample.py
easymaker/storage/__init__.py
easymaker/storage/objectstorage.py
easymaker/training/__init__.py
easymaker/training/components.py
easymaker/training/hyperparameter_tuning.py
easymaker/training/training.py
easymaker-2.1.3.dist-info/METADATA
easymaker-2.1.3.dist-info/WHEEL
easymaker-2.1.3.dist-info/entry_points.txt
easymaker-2.1.3.dist-info/RECORD
