Metadata-Version: 2.4
Name: easymaker
Version: 2.1.3
Summary: AI EasyMaker SDK for Python.
Project-URL: Homepage, https://www.nhncloud.com
Author: NHN Cloud AI EasyMaker Services
License-Expression: Apache-2.0
Keywords: AI EasyMaker,Machine Learning,NHN Cloud
Requires-Python: <4,>=3.10
Requires-Dist: argparse<2,>=1.4.0
Requires-Dist: pydantic<3,>=2.10.5
Requires-Dist: requests<3,>=2.32.3
Requires-Dist: tqdm<5,>=4.67.1
